Helpo/__init__.py
Helpo/core.py
Helpo/helpers.py
pyrohelpo-4.1.5.dist-info/LICENSE
pyrohelpo-4.1.5.dist-info/METADATA
pyrohelpo-4.1.5.dist-info/WHEEL
pyrohelpo-4.1.5.dist-info/top_level.txt
pyrohelpo-4.1.5.dist-info/RECORD
