Metadata-Version: 2.1
Name: pyrohelpo
Version: 4.1.5
Summary: A powerful pagination library for Pyrogram bots
Home-page: https://github.com/vishal-1756/Helpo
Author: Vishal-1756
Author-email: vishalborse199@gmail.com
Keywords: pyrogram,telegram,bot,pagination,help-menu
Classifier: Development Status :: 5 - Production/Stable
Classifier: Intended Audience :: Developers
Classifier: License :: OSI Approved :: MIT License
Classifier: Operating System :: OS Independent
Classifier: Programming Language :: Python :: 3
Classifier: Programming Language :: Python :: 3.7
Classifier: Programming Language :: Python :: 3.8
Classifier: Programming Language :: Python :: 3.9
Classifier: Programming Language :: Python :: 3.10
Classifier: Topic :: Software Development :: Libraries :: Python Modules
Requires-Python: >=3.7
License-File: LICENSE
Requires-Dist: kurigram
Requires-Dist: tgcrypto
